{"state":
 [{"n":0,
   "id":"M",
   "trans":[{"to":5,"weight":"a"},
            {"to":0,"in":"X","out":"X","weight":{"*":["a","a"]}},
            {"to":1,"out":"X","weight":{"*":["b","c"]}},
            {"to":2,"out":"X","weight":{"*":["b","d"]}},
            {"to":3,"in":"X","weight":{"*":[{"*":["a","b"]},"c"]}},
            {"to":4,"in":"X","weight":{"*":[{"*":["a","b"]},"d"]}}]},
  {"n":1,
   "id":"I1",
   "trans":[{"to":5,"weight":"f"},
            {"to":0,"in":"X","out":"X","weight":{"*":["f","a"]}},
            {"to":3,"in":"X","weight":{"*":[{"*":["f","b"]},"c"]}},
            {"to":4,"in":"X","weight":{"*":[{"*":["f","b"]},"d"]}},
            {"to":1,"out":"X","weight":"g"}]},
  {"n":2,
   "id":"I2",
   "trans":[{"to":5,"weight":"p"},
            {"to":0,"in":"X","out":"X","weight":{"*":["p","a"]}},
            {"to":3,"in":"X","weight":{"*":[{"*":["p","b"]},"c"]}},
            {"to":4,"in":"X","weight":{"*":[{"*":["p","b"]},"d"]}},
            {"to":2,"out":"X","weight":"q"}]},
  {"n":3,
   "id":"D1",
   "trans":[{"to":5,"weight":"f"},
            {"to":0,"in":"X","out":"X","weight":"f"},
            {"to":3,"in":"X","weight":"g"}]},
  {"n":4,
   "id":"D2",
   "trans":[{"to":5,"weight":"p"},
            {"to":0,"in":"X","out":"X","weight":"p"},
            {"to":4,"in":"X","weight":"q"}]},
  {"n":5,
   "id":"E"}
 ]
}
